setup.py
src/impaf_fanstatic.egg-info/PKG-INFO
src/impaf_fanstatic.egg-info/SOURCES.txt
src/impaf_fanstatic.egg-info/dependency_links.txt
src/impaf_fanstatic.egg-info/namespace_packages.txt
src/impaf_fanstatic.egg-info/not-zip-safe
src/impaf_fanstatic.egg-info/requires.txt
src/impaf_fanstatic.egg-info/top_level.txt
src/implugin/__init__.py
src/implugin/fanstatic/__init__.py
src/implugin/fanstatic/application.py
src/implugin/fanstatic/controller.py
src/implugin/fanstatic/resources.py
src/implugin/fanstatic/tests/__init__.py
src/implugin/fanstatic/tests/test_application.py
src/implugin/fanstatic/tests/test_controller.py
src/implugin/fanstatic/tests/test_resources.py