Metadata-Version: 1.0
Name: impaf-fanstatic
Version: 0.1.1
Summary: Fanstatic plugin for Impaf.
Home-page: UNKNOWN
Author: UNKNOWN
Author-email: UNKNOWN
License: Apache License 2.0
Platform: UNKNOWN
